catbird/apis/__init__.py
catbird/apis/train.py
catbird/core/__init__.py
catbird/core/utils/__init__.py
catbird/core/utils/config.py
catbird/core/utils/fileio/__init__.py
catbird/core/utils/fileio/handlers/__init__.py
catbird/core/utils/fileio/handlers/base.py
catbird/core/utils/fileio/handlers/json_handler.py
catbird/core/utils/fileio/handlers/yaml_handler.py
catbird/core/utils/fileio/io.py
catbird/core/utils/logging.py
catbird/core/utils/path.py
catbird/datasets/__init__.py
catbird/datasets/builder.py
catbird/datasets/quora.py
catbird/models/__init__.py
catbird/models/builder.py
catbird/models/losses/__init__.py
catbird/models/t5.py
catbird-0.0.2.dist-info/LICENSE
catbird-0.0.2.dist-info/WHEEL
catbird-0.0.2.dist-info/METADATA
catbird-0.0.2.dist-info/RECORD
