Metadata-Version: 2.1
Name: catbird
Version: 0.0.2
Summary: Paraphrase generation Toolbox and Benchmark
Home-page: https://github.com/AfonsoSalgadoSousa/catbird
License: MIT
Keywords: nlp,paraphrase generation
Author: Afonso Sousa
Author-email: afonsousa2806@gmail.com
Requires-Python: >=3.8,<4.0
Classifier: Development Status :: 3 - Alpha
Classifier: Intended Audience :: Developers
Classifier: License :: OSI Approved :: MIT License
Classifier: Operating System :: OS Independent
Classifier: Programming Language :: Python :: 3
Classifier: Programming Language :: Python :: 3.10
Classifier: Programming Language :: Python :: 3.8
Classifier: Programming Language :: Python :: 3.9
Requires-Dist: addict (>=2.4.0,<3.0.0)
Requires-Dist: datasets (>=1.16.1,<2.0.0)
Requires-Dist: pytorch-ignite (>=0.4.7,<0.5.0)
Requires-Dist: sentencepiece (>=0.1.96,<0.2.0)
Requires-Dist: tensorboardX (>=2.4.1,<3.0.0)
Requires-Dist: torch (>=1.10.0,<2.0.0)
Requires-Dist: transformers (>=4.14.1,<5.0.0)
Project-URL: Documentation, https://github.com/AfonsoSalgadoSousa/catbird
Project-URL: Repository, https://github.com/AfonsoSalgadoSousa/catbird
